mvc4kivy/MVC/Model/__init__.py
mvc4kivy/MVC/Model/database_firebase.py
mvc4kivy/MVC/Model/database_restdb.py
mvc4kivy/MVC/__init__.py
mvc4kivy/MVC/data/locales/po/en.po
mvc4kivy/MVC/data/locales/po/ru.po
mvc4kivy/MVC/libs/__init__.py
mvc4kivy/MVC/libs/decorator.py
mvc4kivy/MVC/libs/serialize.py
mvc4kivy/MVC/libs/singleton.py
mvc4kivy/MVC/libs/translation.py
mvc4kivy/MVC/messages.pot
mvc4kivy/__init__.py
mvc4kivy/add_view.py
mvc4kivy/create_project.py
mvc4kivy/remove_view.py
mvc4kivy-1.1.1.dist-info/METADATA
mvc4kivy-1.1.1.dist-info/WHEEL
mvc4kivy-1.1.1.dist-info/entry_points.txt
mvc4kivy-1.1.1.dist-info/RECORD
