Metadata-Version: 2.1
Name: mvc4kivy
Version: 1.1.1
Summary: tool to create MVC project for kivy
Author: Kenechukwu Akubue
Author-email: kengoon19@gmail.com
Requires-Python: >=3.9,<4.0
Classifier: Programming Language :: Python :: 3
Classifier: Programming Language :: Python :: 3.9
Classifier: Programming Language :: Python :: 3.10
Classifier: Programming Language :: Python :: 3.11
Classifier: Programming Language :: Python :: 3.12
Requires-Dist: kivy (>=2.0.0,<3.0.0)
